astrologics/__init__.py
astrologics/logic_analysis.py
astrologics/logical_rules_processing.py
astrologics/model_attractors.py
astrologics/model_simulation.py
astrologics/succession_diagram.py
astrologics/trajectory_clustering.py
astrologics-0.3.0.dist-info/licenses/LICENSE
astrologics-0.3.0.dist-info/METADATA
astrologics-0.3.0.dist-info/WHEEL
astrologics-0.3.0.dist-info/top_level.txt
astrologics-0.3.0.dist-info/RECORD
