Metadata-Version: 2.4
Name: AstroLogics
Version: 0.3.0
Summary: An analysis framework for monotonous Boolean model ensemble
Author-email: Saran Pankaew <saran.pankeaw@curie.fr>, Vincent Noël <vincent.noel@curie.fr>
License-Expression: MIT
Requires-Python: >3.8
License-File: LICENSE
Requires-Dist: pandas
Requires-Dist: numpy
Requires-Dist: scipy
Requires-Dist: scikit-learn
Requires-Dist: tslearn
Requires-Dist: fastcluster
Requires-Dist: tqdm
Requires-Dist: maboss
Requires-Dist: boolsim
Requires-Dist: mpbn
Requires-Dist: seaborn
Dynamic: license-file
